rnmon/Databases.py
rnmon/Logging.py
rnmon/MP.py
rnmon/RNSUtils.py
rnmon/Remotes.py
rnmon/__init__.py
rnmon/__main__.py
rnmon/rnmon.py
rnmon-0.3.3.dist-info/METADATA
rnmon-0.3.3.dist-info/WHEEL
rnmon-0.3.3.dist-info/entry_points.txt
rnmon-0.3.3.dist-info/RECORD
