Metadata-Version: 2.4
Name: rnmon
Version: 0.3.3
Summary: Reticulum Monitoring Daemon
Author: Laura Batalha
License-Expression: MIT
Keywords: exporter,influx,monitoring,reticulum
Requires-Python: >=3.9
Requires-Dist: pyyaml>=6.0.2
Requires-Dist: requests>=2.32.3
Requires-Dist: rns>=0.9.6
